xiaoe/__init__.py
xiaoe/api/__init__.py
xiaoe/api/banner.py
xiaoe/api/column.py
xiaoe/api/combine.py
xiaoe/api/comment.py
xiaoe/api/message.py
xiaoe/api/order.py
xiaoe/api/praise.py
xiaoe/api/purchase.py
xiaoe/api/purchase_user.py
xiaoe/api/resource.py
xiaoe/api/user.py
xiaoe/post/__init__.py
xiaoe/type/__init__.py
xiaoe/type/banner.py
xiaoe/type/base.py
xiaoe/type/column.py
xiaoe/type/combine.py
xiaoe/type/comment.py
xiaoe/type/message.py
xiaoe/type/order.py
xiaoe/type/praise.py
xiaoe/type/purchase.py
xiaoe/type/purchase_user.py
xiaoe/type/resource.py
xiaoe/type/user.py
xiaoe_py-1.0.3.dev3.dist-info/DESCRIPTION.rst
xiaoe_py-1.0.3.dev3.dist-info/METADATA
xiaoe_py-1.0.3.dev3.dist-info/RECORD
xiaoe_py-1.0.3.dev3.dist-info/WHEEL
xiaoe_py-1.0.3.dev3.dist-info/metadata.json
xiaoe_py-1.0.3.dev3.dist-info/top_level.txt
