Metadata-Version: 2.0
Name: xiaoe-py
Version: 1.0.3.dev3
Summary: python package for xiaoe
Home-page: UNKNOWN
Author: ttm1234
Author-email: UNKNOWN
License: MIT
Keywords: xiaoe
Platform: UNKNOWN
Classifier: Intended Audience :: Developers
Classifier: License :: OSI Approved :: MIT License
Classifier: Programming Language :: Python :: 3.5
Classifier: Programming Language :: Python :: 3.6
